<?xml version="1.0" ?>
<tmx version="1.4">
    <header
            creationtool="XYZTool"
            creationtoolversion="1.01-023"
            datatype="PlainText"
            segtype="sentence"
            adminlang="en-us"
            srclang="EN"
            o-tmf="ABCTransMem">
    </header>
    <body>
        <tu tuid="title" datatype="plaintext">
            <tuv xml:lang="uk">
                <seg>Намалюйте та замовте - Створення листівки, пазлів та інших виробів з вашими фотографіями та
                    малюнками- photoprint.in.ua
                </seg>
            </tuv>
            <tuv xml:lang="ru">
                <seg>Нарисуйте и закажите - Создание открытки, пазлов и других изделий с вашими фотографиями и рисунками
                    - photoprint.in.ua
                </seg>
            </tuv>
        </tu>
        <tu tuid="description" datatype="plaintext">
            <tuv xml:lang="uk">
                <seg></seg>
            </tuv>
            <tuv xml:lang="ru">
                <seg></seg>
            </tuv>
        </tu>
        <tu tuid="please_login" datatype="plaintext">
            <tuv xml:lang="uk">
                <seg>Для того щоб зберегти картинку необхідно залогуватись.</seg>
            </tuv>
            <tuv xml:lang="ru">
                <seg>Для того чтобы сохранить картинку необходимо войти.</seg>
            </tuv>
        </tu>

        <tu tuid="postcard_label" datatype="plaintext">
            <tuv xml:lang="uk">
                <seg>листівки</seg>
            </tuv>
            <tuv xml:lang="ru">
                <seg>открытки</seg>
            </tuv>
        </tu>
        <tu tuid="puzzle_label" datatype="plaintext">
            <tuv xml:lang="uk">
                <seg>пазлів</seg>
            </tuv>
            <tuv xml:lang="ru">
                <seg>пазлов</seg>
            </tuv>
        </tu>
        <tu tuid="mousepad_label" datatype="plaintext">
            <tuv xml:lang="uk">
                <seg>килимок</seg>
            </tuv>
            <tuv xml:lang="ru">
                <seg>коврик</seg>
            </tuv>
        </tu>
        <tu tuid="trivet_label" datatype="plaintext">
            <tuv xml:lang="uk">
                <seg>підставки під горнятко</seg>
            </tuv>
            <tuv xml:lang="ru">
                <seg>подставки под чашку</seg>
            </tuv>
        </tu>
    </body>
</tmx>
